[
    {
        "CustomerID":1,
        "Name":"Amit",
        "Age":25,
        "City":"Surat",
        "PurchaseAmount":1200,
        "Churn":"No"
    },
    {
        "CustomerID":2,
        "Name":"Riya",
        "Age":30,
        "City":"Mumbai",
        "PurchaseAmount":1500,
        "Churn":"Yes"
    },
    {
        "CustomerID":3,
        "Name":"Rahul",
        "Age":22,
        "City":"Delhi",
        "PurchaseAmount":800,
        "Churn":"No"
    },
    {
        "CustomerID":4,
        "Name":"Sneha",
        "Age":28,
        "City":"Pune",
        "PurchaseAmount":2000,
        "Churn":"No"
    },
    {
        "CustomerID":5,
        "Name":"Karan",
        "Age":35,
        "City":"Ahmedabad",
        "PurchaseAmount":2500,
        "Churn":"Yes"
    },
    {
        "CustomerID":6,
        "Name":"Neha",
        "Age":27,
        "City":"Jaipur",
        "PurchaseAmount":1100,
        "Churn":"No"
    },
    {
        "CustomerID":7,
        "Name":"Arjun",
        "Age":24,
        "City":"Surat",
        "PurchaseAmount":900,
        "Churn":"No"
    },
    {
        "CustomerID":8,
        "Name":"Pooja",
        "Age":31,
        "City":"Delhi",
        "PurchaseAmount":1800,
        "Churn":"Yes"
    },
    {
        "CustomerID":9,
        "Name":"Vikas",
        "Age":29,
        "City":"Mumbai",
        "PurchaseAmount":1600,
        "Churn":"No"
    },
    {
        "CustomerID":10,
        "Name":"Anjali",
        "Age":26,
        "City":"Pune",
        "PurchaseAmount":1400,
        "Churn":"No"
    }
]